pylocc/__init__.py
pylocc/cli.py
pylocc/file_utils.py
pylocc/processor.py
pylocc/reporter.py
pylocc/language.json
pylocc/language.py
pylocc-1.5.1.dist-info/METADATA
pylocc-1.5.1.dist-info/WHEEL
pylocc-1.5.1.dist-info/entry_points.txt
pylocc-1.5.1.dist-info/licenses/LICENSE
pylocc-1.5.1.dist-info/RECORD
