Metadata-Version: 2.4
Name: pylocc
Version: 1.5.1
Summary: Add your description here
Project-URL: Homepage, https://cirius1792.github.io/pylocc/
Project-URL: Issues, https://github.com/Cirius1792/pylocc/issues
Author-email: Ciro Lucio Tecce <cirolucio.tecce@gmail.com>
License-Expression: MIT
License-File: LICENSE
Requires-Python: >=3.10
Requires-Dist: click>=8.2.1
Requires-Dist: prettytable>=3.16.0
Requires-Dist: pyinstaller>=6.16.0
Requires-Dist: rich>=14.1.0
